tkenginer/__init__.py
tkenginer/engine.py
tkenginer/math.py
tkenginer/mesh.py
tkenginer/node.py
tkenginer/physics.py
tkenginer/transform.py
tkenginer-0.3.0a1.dist-info/METADATA
tkenginer-0.3.0a1.dist-info/WHEEL
tkenginer-0.3.0a1.dist-info/licenses/LICENSE
tkenginer-0.3.0a1.dist-info/RECORD
