Metadata-Version: 2.4
Name: tkenginer
Version: 0.3.0a1
Summary: A fun experimental 3D engine built with Tkinter.
Project-URL: Homepage, https://github.com/IExploitableMan/TkEnginer
Project-URL: Repository, https://github.com/IExploitableMan/TkEnginer.git
Project-URL: Issues, https://github.com/IExploitableMan/TkEnginer/issues
Author: IExploitableMan
License-Expression: CC-BY-NC-ND-4.0
License-File: LICENSE
Keywords: 3d,engine,rendering,tkinter
Classifier: Development Status :: 3 - Alpha
Classifier: Intended Audience :: Developers
Classifier: Intended Audience :: Education
Classifier: Operating System :: OS Independent
Classifier: Programming Language :: Python :: 3
Classifier: Programming Language :: Python :: 3.9
Classifier: Programming Language :: Python :: 3.10
Classifier: Programming Language :: Python :: 3.11
Classifier: Programming Language :: Python :: 3.12
Classifier: Programming Language :: Python :: 3.13
Classifier: Programming Language :: Python :: 3.14
Classifier: Programming Language :: Python :: 3.15
Classifier: Topic :: Multimedia :: Graphics :: 3D Rendering
Classifier: Topic :: Software Development :: Libraries :: Application Frameworks
Classifier: Topic :: Software Development :: Libraries :: Python Modules
Requires-Python: >=3.9
Requires-Dist: numba
Requires-Dist: numpy
Requires-Dist: pillow
